ullm/__init__.py
ullm/alibaba.py
ullm/anthropic.py
ullm/baichuan.py
ullm/baidu.py
ullm/base.py
ullm/bytedance.py
ullm/cli.py
ullm/cloudflare.py
ullm/cohere.py
ullm/deepseek.py
ullm/google.py
ullm/groq.py
ullm/hub.py
ullm/iflytek.py
ullm/minimax.py
ullm/moonshot.py
ullm/ollama.py
ullm/openai.py
ullm/openai_types.py
ullm/openrouter.py
ullm/perplexity.py
ullm/skywork.py
ullm/stepfun.py
ullm/tencent.py
ullm/together.py
ullm/types.py
ullm/zero_one.py
ullm/zhipu.py
ullm-0.14.2.dist-info/METADATA
ullm-0.14.2.dist-info/WHEEL
ullm-0.14.2.dist-info/entry_points.txt
ullm-0.14.2.dist-info/top_level.txt
ullm-0.14.2.dist-info/RECORD
