Metadata-Version: 2.1
Name: ullm
Version: 0.14.2
Summary: A unified interface for local Large Language Model(LLM) models and online LLM providers.
Author-email: Linusp <linusp1024@gmail.com>
Project-URL: Homepage, https://github.com/monsternlp/ullm
Classifier: License :: OSI Approved :: MIT License
Classifier: Programming Language :: Python
Classifier: Programming Language :: Python :: 3
Requires-Python: >=3.8
Requires-Dist: pydantic
Requires-Dist: arrow
Requires-Dist: websocket-client
Requires-Dist: requests
Requires-Dist: python-magic
Requires-Dist: click
Requires-Dist: deepmerge
Requires-Dist: jsonschema
Requires-Dist: tabulate
Requires-Dist: peewee
Requires-Dist: pydantic-settings
Requires-Dist: redis
Provides-Extra: test
Requires-Dist: pytest; extra == "test"
Requires-Dist: pytest-cov; extra == "test"
